src/__init__.py
src/common.py
src/context.py
src/decorators.py
src/oauth.py
src/openai_actions.py
src/stdio_decorators.py
src/stdio_server.py
src/utils.py
src/tools/__init__.py
src/tools/alpha_intelligence.py
src/tools/commodities.py
src/tools/core_stock_apis.py
src/tools/cryptocurrencies.py
src/tools/economic_indicators.py
src/tools/forex.py
src/tools/fundamental_data.py
src/tools/meta_tools.py
src/tools/openai.py
src/tools/options_data_apis.py
src/tools/ping.py
src/tools/registry.py
src/tools/technical_indicators_part1.py
src/tools/technical_indicators_part2.py
src/tools/technical_indicators_part3.py
src/tools/technical_indicators_part4.py
av_mcp-0.3.1.dist-info/METADATA
av_mcp-0.3.1.dist-info/WHEEL
av_mcp-0.3.1.dist-info/entry_points.txt
av_mcp-0.3.1.dist-info/RECORD
