Metadata-Version: 2.4
Name: av-mcp
Version: 0.3.1
Summary: Alpha Vantage MCP Server - Financial data APIs via Model Context Protocol
License: MIT
Requires-Python: >=3.13
Requires-Dist: awslabs-mcp-lambda-handler>=0.1.8
Requires-Dist: click>=8.2.1
Requires-Dist: loguru>=0.7.3
Requires-Dist: mcp>=1.12.3
Requires-Dist: python-dotenv>=1.1.1
